flight/__init__.py
flight/numpy_client.py
flight/numpy_server.py
flight/utils/__init__.py
flight/utils/alter.py
numpy_flight-0.0.14.dist-info/METADATA
numpy_flight-0.0.14.dist-info/WHEEL
numpy_flight-0.0.14.dist-info/licenses/LICENSE
numpy_flight-0.0.14.dist-info/RECORD
