Metadata-Version: 2.4
Name: numpy-flight
Version: 0.0.14
Summary: A little client/server for applications driven by numpy
Project-URL: repository, https://github.com/tschm/numpy-client
Author-email: Thomas Schmelzer <thomas.schmelzer@gmail.com>
License-File: LICENSE
Requires-Python: >=3.10
Requires-Dist: numpy>=2.2.3
Requires-Dist: pyarrow>=19.0.0
Provides-Extra: dev
Requires-Dist: loguru>=0.7.3; extra == 'dev'
Requires-Dist: pre-commit>=4.1.0; extra == 'dev'
Requires-Dist: pytest-cov>=6.0.0; extra == 'dev'
Requires-Dist: pytest-mock>=3.14.0; extra == 'dev'
Requires-Dist: pytest>=8.3.4; extra == 'dev'
